pftracker/__init__.py
pftracker/track.py
pftracker/modules/__init__.py
pftracker/modules/interfacingUI.py
pftracker/modules/runFilter.py
pftracker/modules/facedetection/Face_detection.py
pftracker/modules/facedetection/__init__.py
pftracker/modules/facedetection/models/deploy.prototxt.txt
pftracker/modules/facedetection/models/haarcascade_frontalface_default.xml
pftracker/modules/facedetection/models/haarcascade_profileface.xml
pftracker/modules/facedetection/models/haarcascade_profileface_left2.xml
pftracker/modules/facedetection/models/res10_300x300_ssd_iter_140000.caffemodel
pftracker/modules/filter/Filter.py
pftracker/modules/filter/__init__.py
pftracker/modules/filter/pfAlgorithms.py
pftracker/modules/metrics/PrecRecall.py
pftracker/modules/metrics/__init__.py
pftracker/modules/metrics/eval_2DFace.py
pftracker/modules/metrics/plotError.py
pftracker/modules/metrics/plotErrorTrack.py
pftracker/modules/metrics/plotError_ui.py
pftracker/modules/models/FaceModel_2D.py
pftracker/modules/models/InitModel.py
pftracker/modules/models/ObsModels.py
pftracker/modules/models/__init__.py
pftracker/modules/models/dlgModel.py
pftracker/modules/models/predictBB.py
pftracker/modules/models/colorhist/HSVModel.py
pftracker/modules/models/colorhist/__init__.py
pftracker/modules/models/colorhist/hsvhistogram.py
pftracker/modules/models/lbp/LBPModel.py
pftracker/modules/models/lbp/LBPModel1.py
pftracker/modules/models/lbp/__init__.py
pftracker/modules/models/lbp/lbphistogram.py
pftracker/modules/models/lbp/lbphistogram1.py
pftracker/ui_sources/__init__.py
pftracker/ui_sources/dialog_error_ui.py
pftracker/ui_sources/dialog_facedetector_ui.py
pftracker/ui_sources/dialog_results_ui.py
pftracker/ui_sources/mainwindow_ui.py
pftracker/ui_sources/icons/PFT.PNG
pftracker/ui_sources/icons/cerrar_t.PNG
pftracker/ui_sources/icons/icons8-checkmark (1).svg
pftracker/ui_sources/icons/run_transp.png
pftracker-0.0.2.dist-info/LICENSE
pftracker-0.0.2.dist-info/METADATA
pftracker-0.0.2.dist-info/WHEEL
pftracker-0.0.2.dist-info/top_level.txt
pftracker-0.0.2.dist-info/RECORD
