Metadata-Version: 2.1
Name: pftracker
Version: 0.0.2
Summary: Face tracking based on particle filter
Home-page: https://github.com/bdager/pftracker
Author: Bessie Domínguez-Dáger
Author-email: bessie.dominguez97@gmail.com
License: UNKNOWN
Keywords: Face tracking,particle filter
Platform: UNKNOWN
Classifier: Development Status :: 3 - Alpha
Classifier: Intended Audience :: Developers
Classifier: Intended Audience :: Education
Classifier: Intended Audience :: Science/Research
Classifier: Topic :: Scientific/Engineering
Classifier: Topic :: Scientific/Engineering :: Mathematics
Classifier: Topic :: Scientific/Engineering :: Artificial Intelligence
Classifier: Topic :: Utilities
Classifier: License :: OSI Approved :: GNU General Public License v3 (GPLv3)
Classifier: Programming Language :: Python :: 3
Classifier: Programming Language :: Python :: 3.6
Classifier: Operating System :: Microsoft :: Windows
Requires-Dist: numpy
Requires-Dist: matplotlib
Requires-Dist: opencv-python (==4.2.0)
Requires-Dist: imutils
Requires-Dist: pyqt5
Requires-Dist: scikit-image
Requires-Dist: dlib (==19.8.1)
Requires-Dist: filterpy (==1.4.5)
